glados_alpha/__init__.py
glados_alpha/daughter.py
glados_alpha/filldictionary.py
glados_alpha/glados.py
glados_alpha/nucleus.py
glados_alpha/printinfo.py
glados_alpha/searcher.py
GLaDOS_alpha-3.0.dist-info/METADATA
GLaDOS_alpha-3.0.dist-info/WHEEL
GLaDOS_alpha-3.0.dist-info/entry_points.txt
GLaDOS_alpha-3.0.dist-info/top_level.txt
GLaDOS_alpha-3.0.dist-info/RECORD
