Metadata-Version: 2.1
Name: GLaDOS-alpha
Version: 3.0
Summary: General Lookup of α-Decay for Optimised Search (GLαDOS)
Home-page: https://github.com/Yottaphy/glados
Author: Jorge Romero
Author-email: joromero@jyu.fi
License: GPL-3.0
Platform: UNKNOWN
Requires-Dist: argparse
Requires-Dist: engineering-notation
